{
  "Football": [
    {
      "id": "Cristiano_Ronaldo_4",
      "name": "Cristiano Ronaldo 4",
      "thumbnail": "Cristiano_Ronaldo_4.jpg",
      "video": "Cristiano_Ronaldo_4.mp4",
      "category": "Football"
    },
    {
      "id": "Cristiano_Ronaldo_5",
      "name": "Cristiano Ronaldo 5",
      "thumbnail": "Cristiano_Ronaldo_5.jpg",
      "video": "Cristiano_Ronaldo_5.mp4",
      "category": "Football"
    },
    {
      "id": "Cristiano_Ronaldo_6",
      "name": "Cristiano Ronaldo 6",
      "thumbnail": "Cristiano_Ronaldo_6.jpg",
      "video": "Cristiano_Ronaldo_6.mp4",
      "category": "Football"
    },
    {
      "id": "Cristiano_Ronaldo_Al_Nassr_1",
      "name": "Cristiano Ronaldo Al Nassr 1",
      "thumbnail": "Cristiano_Ronaldo_Al_Nassr_1.jpg",
      "video": "Cristiano_Ronaldo_Al_Nassr_1.mp4",
      "category": "Football"
    },
    {
      "id": "Cristiano_Ronaldo_Al_Nassr_2",
      "name": "Cristiano Ronaldo Al Nassr 2",
      "thumbnail": "Cristiano_Ronaldo_Al_Nassr_2.jpg",
      "video": "Cristiano_Ronaldo_Al_Nassr_2.mp4",
      "category": "Football"
    },
    {
      "id": "Cristiano_Ronaldo_Al_Nassr_3",
      "name": "Cristiano Ronaldo Al Nassr 3",
      "thumbnail": "Cristiano_Ronaldo_Al_Nassr_3.jpg",
      "video": "Cristiano_Ronaldo_Al_Nassr_3.mp4",
      "category": "Football"
    },
    {
      "id": "Cristiano_Ronaldo_Juventus",
      "name": "Cristiano Ronaldo Juventus",
      "thumbnail": "Cristiano_Ronaldo_Juventus.jpg",
      "video": "Cristiano_Ronaldo_Juventus.mp4",
      "category": "Football"
    },
    {
      "id": "Cristiano_Ronaldo_Juventus_1",
      "name": "Cristiano Ronaldo Juventus 1",
      "thumbnail": "Cristiano_Ronaldo_Juventus_1.jpg",
      "video": "Cristiano_Ronaldo_Juventus_1.mp4",
      "category": "Football"
    },
    {
      "id": "Cristiano_Ronaldo_Juventus_2",
      "name": "Cristiano Ronaldo Juventus 2",
      "thumbnail": "Cristiano_Ronaldo_Juventus_2.jpg",
      "video": "Cristiano_Ronaldo_Juventus_2.mp4",
      "category": "Football"
    },
    {
      "id": "Cristiano_Ronaldo_Juventus_3",
      "name": "Cristiano Ronaldo Juventus 3",
      "thumbnail": "Cristiano_Ronaldo_Juventus_3.jpg",
      "video": "Cristiano_Ronaldo_Juventus_3.mp4",
      "category": "Football"
    },
    {
      "id": "Cristiano_Ronaldo_Manchester_United",
      "name": "Cristiano Ronaldo Manchester United",
      "thumbnail": "Cristiano_Ronaldo_Manchester_United.jpg",
      "video": "Cristiano_Ronaldo_Manchester_United.mp4",
      "category": "Football"
    },
    {
      "id": "Cristiano_Ronaldo_Manchester_United_1",
      "name": "Cristiano Ronaldo Manchester United 1",
      "thumbnail": "Cristiano_Ronaldo_Manchester_United_1.jpg",
      "video": "Cristiano_Ronaldo_Manchester_United_1.mp4",
      "category": "Football"
    },
    {
      "id": "Cristiano_Ronaldo_Manchester_United_2",
      "name": "Cristiano Ronaldo Manchester United 2",
      "thumbnail": "Cristiano_Ronaldo_Manchester_United_2.jpg",
      "video": "Cristiano_Ronaldo_Manchester_United_2.mp4",
      "category": "Football"
    },
    {
      "id": "Cristiano_Ronaldo_Manchester_United_3",
      "name": "Cristiano Ronaldo Manchester United 3",
      "thumbnail": "Cristiano_Ronaldo_Manchester_United_3.jpg",
      "video": "Cristiano_Ronaldo_Manchester_United_3.mp4",
      "category": "Football"
    },
    {
      "id": "Cristiano_Ronaldo_Manchester_United_4",
      "name": "Cristiano Ronaldo Manchester United 4",
      "thumbnail": "Cristiano_Ronaldo_Manchester_United_4.jpg",
      "video": "Cristiano_Ronaldo_Manchester_United_4.mp4",
      "category": "Football"
    },
    {
      "id": "Cristiano_Ronaldo_Manchester_United_5",
      "name": "Cristiano Ronaldo Manchester United 5",
      "thumbnail": "Cristiano_Ronaldo_Manchester_United_5.jpg",
      "video": "Cristiano_Ronaldo_Manchester_United_5.mp4",
      "category": "Football"
    },
    {
      "id": "Cristiano_Ronaldo_Manchester_United_6",
      "name": "Cristiano Ronaldo Manchester United 6",
      "thumbnail": "Cristiano_Ronaldo_Manchester_United_6.jpg",
      "video": "Cristiano_Ronaldo_Manchester_United_6.mp4",
      "category": "Football"
    },
    {
      "id": "Cristiano_Ronaldo_Portrait",
      "name": "Cristiano Ronaldo Portrait",
      "thumbnail": "Cristiano_Ronaldo_Portrait.jpg",
      "video": "Cristiano_Ronaldo_Portrait.mp4",
      "category": "Football"
    },
    {
      "id": "Cristiano_Ronaldo_Portugal",
      "name": "Cristiano Ronaldo Portugal",
      "thumbnail": "Cristiano_Ronaldo_Portugal.jpg",
      "video": "Cristiano_Ronaldo_Portugal.mp4",
      "category": "Football"
    },
    {
      "id": "Cristiano_Ronaldo_Portugal_1",
      "name": "Cristiano Ronaldo Portugal 1",
      "thumbnail": "Cristiano_Ronaldo_Portugal_1.jpg",
      "video": "Cristiano_Ronaldo_Portugal_1.mp4",
      "category": "Football"
    },
    {
      "id": "Cristiano_Ronaldo_Portugal_2",
      "name": "Cristiano Ronaldo Portugal 2",
      "thumbnail": "Cristiano_Ronaldo_Portugal_2.png",
      "video": "Cristiano_Ronaldo_Portugal_2.mp4",
      "category": "Football"
    },
    {
      "id": "Cristiano_Ronaldo_Portugal_3",
      "name": "Cristiano Ronaldo Portugal 3",
      "thumbnail": "Cristiano_Ronaldo_Portugal_3.png",
      "video": "Cristiano_Ronaldo_Portugal_3.mp4",
      "category": "Football"
    },
    {
      "id": "Cristiano_Ronaldo_Portugal_4",
      "name": "Cristiano Ronaldo Portugal 4",
      "thumbnail": "Cristiano_Ronaldo_Portugal_4.jpg",
      "video": "Cristiano_Ronaldo_Portugal_4.mp4",
      "category": "Football"
    },
    {
      "id": "Cristiano_Ronaldo_Portugal_5",
      "name": "Cristiano Ronaldo Portugal 5",
      "thumbnail": "Cristiano_Ronaldo_Portugal_5.jpg",
      "video": "Cristiano_Ronaldo_Portugal_5.mp4",
      "category": "Football"
    },
    {
      "id": "Cristiano_Ronaldo_Portugal_6",
      "name": "Cristiano Ronaldo Portugal 6",
      "thumbnail": "Cristiano_Ronaldo_Portugal_6.jpg",
      "video": "Cristiano_Ronaldo_Portugal_6.mp4",
      "category": "Football"
    },
    {
      "id": "Cristiano_Ronaldo_Real_Madrid",
      "name": "Cristiano Ronaldo Real Madrid",
      "thumbnail": "Cristiano_Ronaldo_Real_Madrid.jpg",
      "video": "Cristiano_Ronaldo_Real_Madrid.mp4",
      "category": "Football"
    },
    {
      "id": "Cristiano_Ronaldo_Real_Madrid_1",
      "name": "Cristiano Ronaldo Real Madrid 1",
      "thumbnail": "Cristiano_Ronaldo_Real_Madrid_1.jpg",
      "video": "Cristiano_Ronaldo_Real_Madrid_1.mp4",
      "category": "Football"
    },
    {
      "id": "Cristiano_Ronaldo_Real_Madrid_10",
      "name": "Cristiano Ronaldo Real Madrid 10",
      "thumbnail": "Cristiano_Ronaldo_Real_Madrid_10.png",
      "video": "Cristiano_Ronaldo_Real_Madrid_10.mp4",
      "category": "Football"
    },
    {
      "id": "Cristiano_Ronaldo_Real_Madrid_11",
      "name": "Cristiano Ronaldo Real Madrid 11",
      "thumbnail": "Cristiano_Ronaldo_Real_Madrid_11.jpg",
      "video": "Cristiano_Ronaldo_Real_Madrid_11.mp4",
      "category": "Football"
    },
    {
      "id": "Cristiano_Ronaldo_Real_Madrid_12",
      "name": "Cristiano Ronaldo Real Madrid 12",
      "thumbnail": "Cristiano_Ronaldo_Real_Madrid_12.jpg",
      "video": "Cristiano_Ronaldo_Real_Madrid_12.mp4",
      "category": "Football"
    },
    {
      "id": "Cristiano_Ronaldo_Real_Madrid_13",
      "name": "Cristiano Ronaldo Real Madrid 13",
      "thumbnail": "Cristiano_Ronaldo_Real_Madrid_13.jpg",
      "video": "Cristiano_Ronaldo_Real_Madrid_13.mp4",
      "category": "Football"
    },
    {
      "id": "Cristiano_Ronaldo_Real_Madrid_14",
      "name": "Cristiano Ronaldo Real Madrid 14",
      "thumbnail": "Cristiano_Ronaldo_Real_Madrid_14.jpg",
      "video": "Cristiano_Ronaldo_Real_Madrid_14.mp4",
      "category": "Football"
    },
    {
      "id": "Cristiano_Ronaldo_Real_Madrid_2",
      "name": "Cristiano Ronaldo Real Madrid 2",
      "thumbnail": "Cristiano_Ronaldo_Real_Madrid_2.jpg",
      "video": "Cristiano_Ronaldo_Real_Madrid_2.mp4",
      "category": "Football"
    },
    {
      "id": "Cristiano_Ronaldo_Real_Madrid_3",
      "name": "Cristiano Ronaldo Real Madrid 3",
      "thumbnail": "Cristiano_Ronaldo_Real_Madrid_3.jpg",
      "video": "Cristiano_Ronaldo_Real_Madrid_3.mp4",
      "category": "Football"
    },
    {
      "id": "Cristiano_Ronaldo_Real_Madrid_4",
      "name": "Cristiano Ronaldo Real Madrid 4",
      "thumbnail": "Cristiano_Ronaldo_Real_Madrid_4.png",
      "video": "Cristiano_Ronaldo_Real_Madrid_4.mp4",
      "category": "Football"
    },
    {
      "id": "Cristiano_Ronaldo_Real_Madrid_5",
      "name": "Cristiano Ronaldo Real Madrid 5",
      "thumbnail": "Cristiano_Ronaldo_Real_Madrid_5.png",
      "video": "Cristiano_Ronaldo_Real_Madrid_5.mp4",
      "category": "Football"
    },
    {
      "id": "Cristiano_Ronaldo_Real_Madrid_6",
      "name": "Cristiano Ronaldo Real Madrid 6",
      "thumbnail": "Cristiano_Ronaldo_Real_Madrid_6.png",
      "video": "Cristiano_Ronaldo_Real_Madrid_6.mp4",
      "category": "Football"
    },
    {
      "id": "Cristiano_Ronaldo_Real_Madrid_7",
      "name": "Cristiano Ronaldo Real Madrid 7",
      "thumbnail": "Cristiano_Ronaldo_Real_Madrid_7.png",
      "video": "Cristiano_Ronaldo_Real_Madrid_7.mp4",
      "category": "Football"
    },
    {
      "id": "Cristiano_Ronaldo_Real_Madrid_8",
      "name": "Cristiano Ronaldo Real Madrid 8",
      "thumbnail": "Cristiano_Ronaldo_Real_Madrid_8.png",
      "video": "Cristiano_Ronaldo_Real_Madrid_8.mp4",
      "category": "Football"
    },
    {
      "id": "Cristiano_Ronaldo_Real_Madrid_9",
      "name": "Cristiano Ronaldo Real Madrid 9",
      "thumbnail": "Cristiano_Ronaldo_Real_Madrid_9.png",
      "video": "Cristiano_Ronaldo_Real_Madrid_9.mp4",
      "category": "Football"
    },
    {
      "id": "David_Beckham_Manchester_United_1",
      "name": "David Beckham Manchester United 1",
      "thumbnail": "David_Beckham_Manchester_United_1.jpg",
      "video": "David_Beckham_Manchester_United_1.mp4",
      "category": "Football"
    },
    {
      "id": "Erling_Haaland_Manchester_City",
      "name": "Erling Haaland Manchester City",
      "thumbnail": "Erling_Haaland_Manchester_City.jpg",
      "video": "Erling_Haaland_Manchester_City.mp4",
      "category": "Football"
    },
    {
      "id": "Fiery_Football",
      "name": "Fiery Football",
      "thumbnail": "Fiery_Football.jpg",
      "video": "Fiery_Football.mp4",
      "category": "Football"
    },
    {
      "id": "Karim_Benzema_Real_Madrid_1",
      "name": "Karim Benzema Real Madrid 1",
      "thumbnail": "Karim_Benzema_Real_Madrid_1.jpg",
      "video": "Karim_Benzema_Real_Madrid_1.mp4",
      "category": "Football"
    },
    {
      "id": "Kylian_Mbappe_France",
      "name": "Kylian Mbappe France",
      "thumbnail": "Kylian_Mbappe_France.jpg",
      "video": "Kylian_Mbappe_France.mp4",
      "category": "Football"
    },
    {
      "id": "Kylian_Mbappe_PSG_1",
      "name": "Kylian Mbappe Psg 1",
      "thumbnail": "Kylian_Mbappe_PSG_1.jpg",
      "video": "Kylian_Mbappe_PSG_1.mp4",
      "category": "Football"
    },
    {
      "id": "Kylian_Mbappe_Paris_Saint-Germain",
      "name": "Kylian Mbappe Paris Saint-Germain",
      "thumbnail": "Kylian_Mbappe_Paris_Saint-Germain.jpg",
      "video": "Kylian_Mbappe_Paris_Saint-Germain.mp4",
      "category": "Football"
    },
    {
      "id": "Kylian_Mbappe_Paris_Saint-Germain_2",
      "name": "Kylian Mbappe Paris Saint-Germain 2",
      "thumbnail": "Kylian_Mbappe_Paris_Saint-Germain_2.jpg",
      "video": "Kylian_Mbappe_Paris_Saint-Germain_2.mp4",
      "category": "Football"
    },
    {
      "id": "Kylian_Mbappe_Paris_Saint-Germain_3",
      "name": "Kylian Mbappe Paris Saint-Germain 3",
      "thumbnail": "Kylian_Mbappe_Paris_Saint-Germain_3.jpg",
      "video": "Kylian_Mbappe_Paris_Saint-Germain_3.mp4",
      "category": "Football"
    },
    {
      "id": "Kylian_Mbappe_Paris_Saint-Germain_4",
      "name": "Kylian Mbappe Paris Saint-Germain 4",
      "thumbnail": "Kylian_Mbappe_Paris_Saint-Germain_4.jpg",
      "video": "Kylian_Mbappe_Paris_Saint-Germain_4.mp4",
      "category": "Football"
    },
    {
      "id": "Kylian_Mbappe_Paris_Saint-Germain_5",
      "name": "Kylian Mbappe Paris Saint-Germain 5",
      "thumbnail": "Kylian_Mbappe_Paris_Saint-Germain_5.jpg",
      "video": "Kylian_Mbappe_Paris_Saint-Germain_5.mp4",
      "category": "Football"
    },
    {
      "id": "Kylian_Mbappe_Paris_Saint-Germain_6",
      "name": "Kylian Mbappe Paris Saint-Germain 6",
      "thumbnail": "Kylian_Mbappe_Paris_Saint-Germain_6.jpg",
      "video": "Kylian_Mbappe_Paris_Saint-Germain_6.mp4",
      "category": "Football"
    },
    {
      "id": "Lamine_Yamal_FC_Barcelona",
      "name": "Lamine Yamal Fc Barcelona",
      "thumbnail": "Lamine_Yamal_FC_Barcelona.jpg",
      "video": "Lamine_Yamal_FC_Barcelona.mp4",
      "category": "Football"
    },
    {
      "id": "Lionel_Messi_Argentina",
      "name": "Lionel Messi Argentina",
      "thumbnail": "Lionel_Messi_Argentina.jpg",
      "video": "Lionel_Messi_Argentina.mp4",
      "category": "Football"
    },
    {
      "id": "Lionel_Messi_Argentina_1",
      "name": "Lionel Messi Argentina 1",
      "thumbnail": "Lionel_Messi_Argentina_1.jpg",
      "video": "Lionel_Messi_Argentina_1.mp4",
      "category": "Football"
    },
    {
      "id": "Lionel_Messi_Argentina_10",
      "name": "Lionel Messi Argentina 10",
      "thumbnail": "Lionel_Messi_Argentina_10.png",
      "video": "Lionel_Messi_Argentina_10.mp4",
      "category": "Football"
    },
    {
      "id": "Lionel_Messi_Argentina_11",
      "name": "Lionel Messi Argentina 11",
      "thumbnail": "Lionel_Messi_Argentina_11.png",
      "video": "Lionel_Messi_Argentina_11.mp4",
      "category": "Football"
    },
    {
      "id": "Lionel_Messi_Argentina_12",
      "name": "Lionel Messi Argentina 12",
      "thumbnail": "Lionel_Messi_Argentina_12.jpg",
      "video": "Lionel_Messi_Argentina_12.mp4",
      "category": "Football"
    },
    {
      "id": "Lionel_Messi_Argentina_13",
      "name": "Lionel Messi Argentina 13",
      "thumbnail": "Lionel_Messi_Argentina_13.jpg",
      "video": "Lionel_Messi_Argentina_13.mp4",
      "category": "Football"
    },
    {
      "id": "Lionel_Messi_Argentina_14",
      "name": "Lionel Messi Argentina 14",
      "thumbnail": "Lionel_Messi_Argentina_14.jpg",
      "video": "Lionel_Messi_Argentina_14.mp4",
      "category": "Football"
    },
    {
      "id": "Lionel_Messi_Argentina_15",
      "name": "Lionel Messi Argentina 15",
      "thumbnail": "Lionel_Messi_Argentina_15.jpg",
      "video": "Lionel_Messi_Argentina_15.mp4",
      "category": "Football"
    },
    {
      "id": "Lionel_Messi_Argentina_16",
      "name": "Lionel Messi Argentina 16",
      "thumbnail": "Lionel_Messi_Argentina_16.jpg",
      "video": "Lionel_Messi_Argentina_16.mp4",
      "category": "Football"
    },
    {
      "id": "Lionel_Messi_Argentina_2",
      "name": "Lionel Messi Argentina 2",
      "thumbnail": "Lionel_Messi_Argentina_2.jpg",
      "video": "Lionel_Messi_Argentina_2.mp4",
      "category": "Football"
    },
    {
      "id": "Lionel_Messi_Argentina_3",
      "name": "Lionel Messi Argentina 3",
      "thumbnail": "Lionel_Messi_Argentina_3.jpg",
      "video": "Lionel_Messi_Argentina_3.mp4",
      "category": "Football"
    },
    {
      "id": "Lionel_Messi_Argentina_4",
      "name": "Lionel Messi Argentina 4",
      "thumbnail": "Lionel_Messi_Argentina_4.jpg",
      "video": "Lionel_Messi_Argentina_4.mp4",
      "category": "Football"
    },
    {
      "id": "Lionel_Messi_Argentina_5",
      "name": "Lionel Messi Argentina 5",
      "thumbnail": "Lionel_Messi_Argentina_5.jpg",
      "video": "Lionel_Messi_Argentina_5.mp4",
      "category": "Football"
    },
    {
      "id": "Lionel_Messi_Argentina_6",
      "name": "Lionel Messi Argentina 6",
      "thumbnail": "Lionel_Messi_Argentina_6.jpg",
      "video": "Lionel_Messi_Argentina_6.mp4",
      "category": "Football"
    },
    {
      "id": "Lionel_Messi_Argentina_7",
      "name": "Lionel Messi Argentina 7",
      "thumbnail": "Lionel_Messi_Argentina_7.jpg",
      "video": "Lionel_Messi_Argentina_7.mp4",
      "category": "Football"
    },
    {
      "id": "Lionel_Messi_Argentina_8",
      "name": "Lionel Messi Argentina 8",
      "thumbnail": "Lionel_Messi_Argentina_8.png",
      "video": "Lionel_Messi_Argentina_8.mp4",
      "category": "Football"
    },
    {
      "id": "Lionel_Messi_Argentina_9",
      "name": "Lionel Messi Argentina 9",
      "thumbnail": "Lionel_Messi_Argentina_9.png",
      "video": "Lionel_Messi_Argentina_9.mp4",
      "category": "Football"
    },
    {
      "id": "Lionel_Messi_Art",
      "name": "Lionel Messi Art",
      "thumbnail": "Lionel_Messi_Art.jpg",
      "video": "Lionel_Messi_Art.mp4",
      "category": "Football"
    },
    {
      "id": "Lionel_Messi_Barcelona_2",
      "name": "Lionel Messi Barcelona 2",
      "thumbnail": "Lionel_Messi_Barcelona_2.jpg",
      "video": "Lionel_Messi_Barcelona_2.mp4",
      "category": "Football"
    },
    {
      "id": "Lionel_Messi_Barcelona_3",
      "name": "Lionel Messi Barcelona 3",
      "thumbnail": "Lionel_Messi_Barcelona_3.png",
      "video": "Lionel_Messi_Barcelona_3.mp4",
      "category": "Football"
    },
    {
      "id": "Lionel_Messi_Inter_Miami",
      "name": "Lionel Messi Inter Miami",
      "thumbnail": "Lionel_Messi_Inter_Miami.jpg",
      "video": "Lionel_Messi_Inter_Miami.mp4",
      "category": "Football"
    },
    {
      "id": "Lionel_Messi_Inter_Miami_1",
      "name": "Lionel Messi Inter Miami 1",
      "thumbnail": "Lionel_Messi_Inter_Miami_1.jpg",
      "video": "Lionel_Messi_Inter_Miami_1.mp4",
      "category": "Football"
    },
    {
      "id": "Lionel_Messi_PSG_1",
      "name": "Lionel Messi Psg 1",
      "thumbnail": "Lionel_Messi_PSG_1.png",
      "video": "Lionel_Messi_PSG_1.mp4",
      "category": "Football"
    },
    {
      "id": "Lionel_Messi_PSG_2",
      "name": "Lionel Messi Psg 2",
      "thumbnail": "Lionel_Messi_PSG_2.png",
      "video": "Lionel_Messi_PSG_2.mp4",
      "category": "Football"
    },
    {
      "id": "Logo_AC_Milan",
      "name": "Logo Ac Milan",
      "thumbnail": "Logo_AC_Milan.jpg",
      "video": "Logo_AC_Milan.mp4",
      "category": "Football"
    },
    {
      "id": "Logo_Arsenal",
      "name": "Logo Arsenal",
      "thumbnail": "Logo_Arsenal.jpg",
      "video": "Logo_Arsenal.mp4",
      "category": "Football"
    },
    {
      "id": "Logo_Arsenal_1",
      "name": "Logo Arsenal 1",
      "thumbnail": "Logo_Arsenal_1.png",
      "video": "Logo_Arsenal_1.mp4",
      "category": "Football"
    },
    {
      "id": "Logo_Arsenal_2",
      "name": "Logo Arsenal 2",
      "thumbnail": "Logo_Arsenal_2.jpg",
      "video": "Logo_Arsenal_2.mp4",
      "category": "Football"
    },
    {
      "id": "Logo_Atletico_Madrid",
      "name": "Logo Atletico Madrid",
      "thumbnail": "Logo_Atletico_Madrid.jpg",
      "video": "Logo_Atletico_Madrid.mp4",
      "category": "Football"
    },
    {
      "id": "Logo_Barcelona_1",
      "name": "Logo Barcelona 1",
      "thumbnail": "Logo_Barcelona_1.png",
      "video": "Logo_Barcelona_1.mp4",
      "category": "Football"
    },
    {
      "id": "Logo_Borussia_Dortmund",
      "name": "Logo Borussia Dortmund",
      "thumbnail": "Logo_Borussia_Dortmund.jpg",
      "video": "Logo_Borussia_Dortmund.mp4",
      "category": "Football"
    },
    {
      "id": "Logo_Chelsea_1",
      "name": "Logo Chelsea 1",
      "thumbnail": "Logo_Chelsea_1.png",
      "video": "Logo_Chelsea_1.mp4",
      "category": "Football"
    },
    {
      "id": "Logo_Chelsea_2",
      "name": "Logo Chelsea 2",
      "thumbnail": "Logo_Chelsea_2.jpg",
      "video": "Logo_Chelsea_2.mp4",
      "category": "Football"
    },
    {
      "id": "Logo_Chelsea_3",
      "name": "Logo Chelsea 3",
      "thumbnail": "Logo_Chelsea_3.jpg",
      "video": "Logo_Chelsea_3.mp4",
      "category": "Football"
    },
    {
      "id": "Logo_FC_Barcelona_1",
      "name": "Logo Fc Barcelona 1",
      "thumbnail": "Logo_FC_Barcelona_1.jpg",
      "video": "Logo_FC_Barcelona_1.mp4",
      "category": "Football"
    },
    {
      "id": "Logo_FC_Barcelona_2",
      "name": "Logo Fc Barcelona 2",
      "thumbnail": "Logo_FC_Barcelona_2.jpg",
      "video": "Logo_FC_Barcelona_2.mp4",
      "category": "Football"
    },
    {
      "id": "Logo_FC_Barcelona_3",
      "name": "Logo Fc Barcelona 3",
      "thumbnail": "Logo_FC_Barcelona_3.jpg",
      "video": "Logo_FC_Barcelona_3.mp4",
      "category": "Football"
    },
    {
      "id": "Logo_FC_Barcelona_4",
      "name": "Logo Fc Barcelona 4",
      "thumbnail": "Logo_FC_Barcelona_4.jpg",
      "video": "Logo_FC_Barcelona_4.mp4",
      "category": "Football"
    },
    {
      "id": "Logo_FC_Barcelona_5",
      "name": "Logo Fc Barcelona 5",
      "thumbnail": "Logo_FC_Barcelona_5.jpg",
      "video": "Logo_FC_Barcelona_5.mp4",
      "category": "Football"
    },
    {
      "id": "Logo_FC_Barcelona_6",
      "name": "Logo Fc Barcelona 6",
      "thumbnail": "Logo_FC_Barcelona_6.jpg",
      "video": "Logo_FC_Barcelona_6.mp4",
      "category": "Football"
    },
    {
      "id": "Logo_FIFA_18",
      "name": "Logo Fifa 18",
      "thumbnail": "Logo_FIFA_18.jpg",
      "video": "Logo_FIFA_18.mp4",
      "category": "Football"
    },
    {
      "id": "Logo_Liverpool",
      "name": "Logo Liverpool",
      "thumbnail": "Logo_Liverpool.jpg",
      "video": "Logo_Liverpool.mp4",
      "category": "Football"
    },
    {
      "id": "Logo_Liverpool_1",
      "name": "Logo Liverpool 1",
      "thumbnail": "Logo_Liverpool_1.png",
      "video": "Logo_Liverpool_1.mp4",
      "category": "Football"
    },
    {
      "id": "Logo_Liverpool_2",
      "name": "Logo Liverpool 2",
      "thumbnail": "Logo_Liverpool_2.jpg",
      "video": "Logo_Liverpool_2.mp4",
      "category": "Football"
    },
    {
      "id": "Logo_Manchester_City",
      "name": "Logo Manchester City",
      "thumbnail": "Logo_Manchester_City.jpg",
      "video": "Logo_Manchester_City.mp4",
      "category": "Football"
    },
    {
      "id": "Logo_Manchester_United",
      "name": "Logo Manchester United",
      "thumbnail": "Logo_Manchester_United.jpg",
      "video": "Logo_Manchester_United.mp4",
      "category": "Football"
    },
    {
      "id": "Logo_Manchester_United_1",
      "name": "Logo Manchester United 1",
      "thumbnail": "Logo_Manchester_United_1.png",
      "video": "Logo_Manchester_United_1.mp4",
      "category": "Football"
    },
    {
      "id": "Logo_Real_Madrid",
      "name": "Logo Real Madrid",
      "thumbnail": "Logo_Real_Madrid.jpg",
      "video": "Logo_Real_Madrid.mp4",
      "category": "Football"
    },
    {
      "id": "Logo_Real_Madrid_1",
      "name": "Logo Real Madrid 1",
      "thumbnail": "Logo_Real_Madrid_1.png",
      "video": "Logo_Real_Madrid_1.mp4",
      "category": "Football"
    },
    {
      "id": "Logo_Real_Madrid_2",
      "name": "Logo Real Madrid 2",
      "thumbnail": "Logo_Real_Madrid_2.jpg",
      "video": "Logo_Real_Madrid_2.mp4",
      "category": "Football"
    },
    {
      "id": "Logo_Tottenham_Hotspur",
      "name": "Logo Tottenham Hotspur",
      "thumbnail": "Logo_Tottenham_Hotspur.jpg",
      "video": "Logo_Tottenham_Hotspur.mp4",
      "category": "Football"
    },
    {
      "id": "Mohamed_Salah_Liverpool_1",
      "name": "Mohamed Salah Liverpool 1",
      "thumbnail": "Mohamed_Salah_Liverpool_1.jpg",
      "video": "Mohamed_Salah_Liverpool_1.mp4",
      "category": "Football"
    },
    {
      "id": "Mykhailo_Mudryk_Shakhtar_Donetsk",
      "name": "Mykhailo Mudryk Shakhtar Donetsk",
      "thumbnail": "Mykhailo_Mudryk_Shakhtar_Donetsk.jpg",
      "video": "Mykhailo_Mudryk_Shakhtar_Donetsk.mp4",
      "category": "Football"
    },
    {
      "id": "Neymar_Jr_Brazil",
      "name": "Neymar Jr Brazil",
      "thumbnail": "Neymar_Jr_Brazil.jpg",
      "video": "Neymar_Jr_Brazil.mp4",
      "category": "Football"
    },
    {
      "id": "Neymar_Jr_PSG_1",
      "name": "Neymar Jr Psg 1",
      "thumbnail": "Neymar_Jr_PSG_1.jpg",
      "video": "Neymar_Jr_PSG_1.mp4",
      "category": "Football"
    },
    {
      "id": "Neymar_Jr_Paris_Saint-Germain",
      "name": "Neymar Jr Paris Saint-Germain",
      "thumbnail": "Neymar_Jr_Paris_Saint-Germain.jpg",
      "video": "Neymar_Jr_Paris_Saint-Germain.mp4",
      "category": "Football"
    },
    {
      "id": "Neymar_Jr_Paris_Saint-Germain_2",
      "name": "Neymar Jr Paris Saint-Germain 2",
      "thumbnail": "Neymar_Jr_Paris_Saint-Germain_2.jpg",
      "video": "Neymar_Jr_Paris_Saint-Germain_2.mp4",
      "category": "Football"
    },
    {
      "id": "Neymar_Jr_Paris_Saint-Germain_3",
      "name": "Neymar Jr Paris Saint-Germain 3",
      "thumbnail": "Neymar_Jr_Paris_Saint-Germain_3.jpg",
      "video": "Neymar_Jr_Paris_Saint-Germain_3.mp4",
      "category": "Football"
    },
    {
      "id": "Neymar_Jr_Paris_Saint-Germain_4",
      "name": "Neymar Jr Paris Saint-Germain 4",
      "thumbnail": "Neymar_Jr_Paris_Saint-Germain_4.jpg",
      "video": "Neymar_Jr_Paris_Saint-Germain_4.mp4",
      "category": "Football"
    },
    {
      "id": "Neymar_Jr_Paris_Saint-Germain_5",
      "name": "Neymar Jr Paris Saint-Germain 5",
      "thumbnail": "Neymar_Jr_Paris_Saint-Germain_5.jpg",
      "video": "Neymar_Jr_Paris_Saint-Germain_5.mp4",
      "category": "Football"
    },
    {
      "id": "Neymar_Jr_Paris_Saint-Germain_6",
      "name": "Neymar Jr Paris Saint-Germain 6",
      "thumbnail": "Neymar_Jr_Paris_Saint-Germain_6.jpg",
      "video": "Neymar_Jr_Paris_Saint-Germain_6.mp4",
      "category": "Football"
    },
    {
      "id": "Neymar_Jr_Paris_Saint-Germain_7",
      "name": "Neymar Jr Paris Saint-Germain 7",
      "thumbnail": "Neymar_Jr_Paris_Saint-Germain_7.jpg",
      "video": "Neymar_Jr_Paris_Saint-Germain_7.mp4",
      "category": "Football"
    },
    {
      "id": "PSG_Colors",
      "name": "Psg Colors",
      "thumbnail": "PSG_Colors.jpg",
      "video": "PSG_Colors.mp4",
      "category": "Football"
    },
    {
      "id": "Palmeiras_Player",
      "name": "Palmeiras Player",
      "thumbnail": "Palmeiras_Player.jpg",
      "video": "Palmeiras_Player.mp4",
      "category": "Football"
    },
    {
      "id": "Pixel_Art_Football",
      "name": "Pixel Art Football",
      "thumbnail": "Pixel_Art_Football.jpg",
      "video": "Pixel_Art_Football.mp4",
      "category": "Football"
    },
    {
      "id": "Salem_Al-Dawsari_Al_Hilal",
      "name": "Salem Al-Dawsari Al Hilal",
      "thumbnail": "Salem_Al-Dawsari_Al_Hilal.jpg",
      "video": "Salem_Al-Dawsari_Al_Hilal.mp4",
      "category": "Football"
    },
    {
      "id": "Space_Football",
      "name": "Space Football",
      "thumbnail": "Space_Football.jpg",
      "video": "Space_Football.mp4",
      "category": "Football"
    }
  ]
}